README.txt
setup.cfg
setup.py
nfg/__init__.py
nfg.webfonts.egg-info/PKG-INFO
nfg.webfonts.egg-info/SOURCES.txt
nfg.webfonts.egg-info/dependency_links.txt
nfg.webfonts.egg-info/entry_points.txt
nfg.webfonts.egg-info/namespace_packages.txt
nfg.webfonts.egg-info/not-zip-safe
nfg.webfonts.egg-info/requires.txt
nfg.webfonts.egg-info/top_level.txt
nfg/webfonts/__init__.py
nfg/webfonts/browser.py
nfg/webfonts/interfaces.py
nfg/webfonts/tests.py