Metadata-Version: 1.0
Name: nfg.webfonts
Version: 1.1dev
Summary: Plone integration for WebFonts.biz
Home-page: https://github.com/pjstevns/nfg.webfonts
Author: NFG Net Facilities Group BV
Author-email: support@nfg.nl
License: GPL
Keywords: webfonts
Platform: UNKNOWN
Classifier: Framework :: Plone
Classifier: Programming Language :: Python
Classifier: Topic :: Software Development :: Libraries :: Python Modules
